cliagramme/__init__.py
cliagramme/__main__.py
cliagramme/baton.py
cliagramme/boite.py
cliagramme/rectangulaire.py
cliagramme-1.0.1.dist-info/METADATA
cliagramme-1.0.1.dist-info/WHEEL
cliagramme-1.0.1.dist-info/top_level.txt
cliagramme-1.0.1.dist-info/RECORD
