Metadata-Version: 2.1
Name: cliagramme
Version: 1.0.1
Summary: Afficher et gérer des diagrammes en console.
Home-page: https://github.com/4surix/cliagramme
Author: Asurix
Author-email: asurix@outlook.fr
License: UNKNOWN
Keywords: diagramme cli console shell
Platform: UNKNOWN
Classifier: Programming Language :: Python :: 3 :: Only
Requires-Python: >=3.6, <4
Requires-Dist: colorama (>=0.4.3)
